adafruit_st7565.py
adafruit_circuitpython_st7565-1.1.14.dist-info/licenses/LICENSE
adafruit_circuitpython_st7565-1.1.14.dist-info/METADATA
adafruit_circuitpython_st7565-1.1.14.dist-info/WHEEL
adafruit_circuitpython_st7565-1.1.14.dist-info/top_level.txt
adafruit_circuitpython_st7565-1.1.14.dist-info/RECORD
