Metadata-Version: 2.4
Name: adafruit-circuitpython-st7565
Version: 1.1.14
Summary: CircuitPython display control library for devices using the ST7565 graphic display driver IC.
Author-email: Adafruit Industries <circuitpython@adafruit.com>
License: MIT
Project-URL: Homepage, https://github.com/adafruit/Adafruit_CircuitPython_ST7565
Keywords: adafruit,display,st7565,monochrome,displays,hardware,micropython,circuitpython
Classifier: Intended Audience :: Developers
Classifier: Topic :: Software Development :: Libraries
Classifier: Topic :: Software Development :: Embedded Systems
Classifier: Topic :: System :: Hardware
Classifier: License :: OSI Approved :: MIT License
Classifier: Programming Language :: Python :: 3
License-File: LICENSE
Requires-Dist: Adafruit-Blinka
Requires-Dist: adafruit-circuitpython-busdevice
Requires-Dist: adafruit-circuitpython-framebuf
Provides-Extra: optional
Dynamic: license-file
